snakemake_interface_logger_plugins/__init__.py
snakemake_interface_logger_plugins/base.py
snakemake_interface_logger_plugins/common.py
snakemake_interface_logger_plugins/py.typed
snakemake_interface_logger_plugins/settings.py
snakemake_interface_logger_plugins/registry/__init__.py
snakemake_interface_logger_plugins/registry/plugin.py
snakemake_interface_logger_plugins-1.2.5.dist-info/METADATA
snakemake_interface_logger_plugins-1.2.5.dist-info/WHEEL
snakemake_interface_logger_plugins-1.2.5.dist-info/licenses/LICENSE
snakemake_interface_logger_plugins-1.2.5.dist-info/RECORD
