Metadata-Version: 2.4
Name: snakemake-interface-logger-plugins
Version: 1.2.5
Summary: Logger plugin interface for snakemake
Author: Cade Mirchandani, Christopher Tomkins-Tinch, Johannes Köster
License-File: LICENSE
Requires-Python: <4.0,>=3.11
Requires-Dist: snakemake-interface-common>=1.17.4
